slurm_emission/__init__.py
slurm_emission/submit_jobs.py
slurm_emission-0.1.0.dist-info/licenses/LICENSE
slurm_emission-0.1.0.dist-info/METADATA
slurm_emission-0.1.0.dist-info/WHEEL
slurm_emission-0.1.0.dist-info/top_level.txt
slurm_emission-0.1.0.dist-info/RECORD
