Metadata-Version: 2.4
Name: slurm_emission
Version: 0.1.0
Summary: Submit jobs to SLURM seamlessly
Author-email: Luca Herrtti <luca.herrtti@gmail.com>
License-Expression: MIT
Project-URL: Homepage, https://github.com/lucehe/slurm-emission
Project-URL: Issues, https://github.com/lucehe/slurm-emission/issues
Keywords: slurm,jobs,emission,hpc,sbatch,supercomputer,cluster
Classifier: Programming Language :: Python :: 3
Classifier: Operating System :: OS Independent
Requires-Python: >=3.9
License-File: LICENSE
Dynamic: license-file
